{
  "project_info": {
    "project_number": "220089926727",
    "firebase_url": "https://o-sindico.firebaseio.com",
    "project_id": "o-sindico",
    "storage_bucket": "o-sindico.appspot.com"
  },
  "client": [
    {
      "client_info": {
        "mobilesdk_app_id": "1:220089926727:android:a48a32c669c7782b",
        "android_client_info": {
          "package_name": "com.osindico.android"
        }
      },
      "oauth_client": [
        {
          "client_id": "220089926727-rqstedc56m59si28ab7littbn70q8dcv.apps.googleusercontent.com",
          "client_type": 3
        }
      ],
      "api_key": [
        {
          "current_key": "AIzaSyAuKItAooZLUuvfRlAZYSWkHc7j6e2TY90"
        }
      ],
      "services": {
        "analytics_service": {
          "status": 1
        },
        "appinvite_service": {
          "status": 1,
          "other_platform_oauth_client": []
        },
        "ads_service": {
          "status": 2
        }
      }
    }
  ],
  "configuration_version": "1"
}